visualiser/__init__.py
visualiser/visualiser.py
recursion_visualiser-1.0.3.dist-info/LICENSE.md
recursion_visualiser-1.0.3.dist-info/METADATA
recursion_visualiser-1.0.3.dist-info/WHEEL
recursion_visualiser-1.0.3.dist-info/top_level.txt
recursion_visualiser-1.0.3.dist-info/RECORD
