Metadata-Version: 2.1
Name: recursion-visualiser
Version: 1.0.3
Summary: A small python package to visualise recursive function on Python. It draws recursion tree
Home-page: https://github.com/Bishalsarang/Recursion-Tree-Visualizer
Author: Bishal Sarangkoti
Author-email: sarangbishal@gmail.com
Classifier: Programming Language :: Python :: 3
Classifier: License :: OSI Approved :: MIT License
Classifier: Operating System :: OS Independent
Requires-Python: >=3.6
License-File: LICENSE.md
